onono/__init__.py
onono/__main__.py
onono/app.py
onono/gamelogic.py
onono/gui_definitions.py
onono/image.py
onono/menu.py
onono/savegame.py
onono-1.0.1.dist-info/METADATA
onono-1.0.1.dist-info/WHEEL
onono-1.0.1.dist-info/top_level.txt
onono-1.0.1.dist-info/RECORD
