Metadata-Version: 2.1
Name: onono
Version: 1.0.1
Summary: Onono! The Puzzle Game
Author-email: Simon Ruzicka <sima.ruzicka@gmail.com>
Project-URL: Homepage, https://github.com/ruzicka02/onono
Classifier: Programming Language :: Python :: 3
Classifier: License :: OSI Approved :: MIT License
Classifier: Operating System :: OS Independent
Requires-Python: >=3.9
Requires-Dist: numpy (>=1.23)
Requires-Dist: pygame
Requires-Dist: Pillow (>=9)
Requires-Dist: colorthief
